[{"MOHAWK MOUNTAIN": {"lifts": 0, "trails": 0, "depth": "", "new snow": ""}}, {"MOUNT SOUTHINGTON": {"trails": 0, "lifts": 0, "depth": 0}}, {"POWDER RIDGE": {"trails": 0, "lifts": 0, "depth": 24}}, {"SKI SUNDOWN": {"lifts": 0, "trails": 0, "depth": "", "new snow": ""}}, {"BIGROCK": {"trails": 29, "lifts": 4, "depth": 18, "new snow": 2.0}}, {"BLACK MOUNTAIN ME": {"lifts": 2, "trails": 29, "depth": " 15", "new snow": " 2"}}, {"CAMDEN SNOW BOWL": {"lifts": 0, "trails": 0, "new snow": 0}}, {"LOST VALLEY": {"trails": ""}}, {"MOUNT ABRAM": {"trails": 0, "lifts": 0}}, {"SADDLEBACK": {"lifts": 6, "trails": 67, "new snow": 3, "depth": 30}}, {"PLEASANT MOUNTAIN": {"trails": 28, "lifts": 5, "new snow": 1}}, {"SUGARLOAF": {"trails": 141, "lifts": 7, "new snow": 3}}, {"SUNDAY RIVER": {"trails": 117, "lifts": 11, "new snow": 1}}, {"BERKSHIRE EAST": {"trails": 28, "lifts": 3, "depth": 12, "new snow": 0}}, {"BOUSQUET": {"trails": 11, "lifts": 0}}, {"CATAMOUNT": {"trails": 20, "lifts": 3, "depth": 12.0, "new snow": 0}}, {"JIMINY PEAK": {"trails": 0, "lifts": 0, "depth": 12, "new snow": 0}}, {"NASHOBA VALLEY": {"trails": 0, "lifts": 0, "depth": 28, "new snow": 0}}, {"BRADFORD": {"trails": 0}}, {"BUTTERNUT": {"lifts": 0, "trails": 0, "depth": "", "new snow": ""}}, {"SKI WARD": {"trails": 0, "lifts": 0, "depth": 12}}, {"WACHUSETT": {"trails": 25, "lifts": 5, "depth": 35, "new snow": 0}}, {"ATTITASH": {"trails": 53, "lifts": 7, "depth": 23, "new snow": 2}}, {"BRETTON WOODS": {"trails": 56, "lifts": 4, "depth": 28, "new snow": 1}}, {"BLACK MOUNTAIN NH": {"trails": 0, "lifts": 0}}, {"CANNON MOUNTAIN": {"trails": 79, "lifts": 5, "depth": 20, "new snow": 0}}, {"CRANMORE": {"trails": 37, "lifts": 2, "depth": 15, "new snow": 4}}, {"CROTCHED": {"trails": 0, "lifts": 0, "depth": 40, "new snow": 0}}, {"DARTMOUTH SKIWAY": {"lifts": 4, "trails": 25, "new snow": 2}}, {"KING PINE": {"trails": 0, "lifts": 0, "depth": null, "new snow": null}}, {"LOON Mountain": {"lifts": 8, "trails": 52, "new snow": 6}}, {"MOUNT SUNAPEE": {"trails": 52, "lifts": 6, "depth": 76, "new snow": 2}}, {"PATS PEAK": {"trails": 0, "lifts": 0, "depth": 0, "new snow": 0}}, {"RAGGED MOUNTAIN": {"trails": 34, "lifts": 5, "depth": 12, "new snow": 2}}, {"WATERVILLE VALLEY": {"trails": 62, "lifts": 6, "depth": 18, "new snow": 0}}, {"WHALEBACK": {"trails": 0, "lifts": 0, "depth": 8, "new snow": 0}}, {"WILDCAT": {"trails": 48, "lifts": 4, "depth": 50, "new snow": 3}}, {"YAWGOO VALLEY": {"trails": 0, "lifts": 0}}, {"BOLTON VALLEY": {"trails": 71, "lifts": 6, "depth": 12, "new snow": 2}}, {"BROMLEY": {"trails": 42, "lifts": 2, "depth": 8, "new snow": 0}}, {"BURKE": {"trails": 52, "lifts": 4}}, {"JAY PEAK": {"trails": 81, "lifts": 7, "depth": 45, "new snow": 2}}, {"KILLINGTON": {"trails": 154, "lifts": 17, "depth": 26, "new snow": 5}}, {"MAD RIVER GLEN": {"trails": 53, "lifts": 4, "new snow": 7}}, {"MAGIC MOUNTAIN": {"trails": 46, "lifts": 2, "new snow": 2}}, {"MIDDLEBURY SNOW BOWL": {"trails": 11, "lifts": 0, "depth": 12, "new snow": 2}}, {"MOUNT SNOW": {"trails": 65, "lifts": 6, "depth": 30, "new snow": 0}}, {"OKEMO": {"trails": 123, "lifts": 14, "depth": 24, "new snow": 1}}, {"SMUGGLERS NOTCH": {"trails": 50, "lifts": 4, "new snow": 2}}, {"STOWE": {"trails": 99, "lifts": 7, "depth": 50, "new snow": 3}}, {"STRATTON": {"trails": 83, "lifts": 6, "depth": 35.0}}, {"SUGARBUSH": {"trails": 100, "lifts": 9, "depth": 32.0, "new snow": 4.0}}]