[
  {"MOHAWK MOUNTAIN":{"closed":true}},
  {"MOUNT SOUTHINGTON":{"closed":true}},
  {"POWDER RIDGE":{"closed":true}},
  {"SKI SUNDOWN":{"closed":true}},
  {"BIG MOOSE MOUNTAIN":{"closed":true}},
  {"BIGROCK":{"closed":true}},
  {"BLACK MOUNTAIN ME":{"closed":true}},
  {"CAMDEN SNOW BOWL":{"closed":true}},
  {"LOST VALLEY":{"closed":true}},
  {"MOUNT ABRAM":{"closed":true}},
  {"PLEASANT MOUNTAIN":{"trails":0,"lifts":0,"new snow":0,"depth":0}},
  {"SADDLEBACK":{"trails":49,"lifts":1,"new snow":0,"depth":30}},
  {"SUGARLOAF":{"trails":48,"lifts":4,"new snow":2,"depth":25}},
  {"SUNDAY RIVER":{"trails":47,"lifts":3,"new snow":0,"depth":20}},
  {"BERKSHIRE EAST":{"trails":28,"lifts":0,"new snow":0,"depth":0}},
  {"BLUE HILLS":{"closed":true}},
  {"BOUSQUET":{"closed":true}},
  {"CATAMOUNT":{"trails":0,"lifts":0,"new snow":0,"depth":0}},
  {"JIMINY PEAK":{"trails":19,"lifts":3,"new snow":0,"depth":10}},
  {"NASHOBA VALLEY":{"closed":true}},
  {"SKI BRADFORD":{"closed":true}},
  {"BUTTERNUT":{"closed":true}},
  {"OTIS RIDGE":{"closed":true}},
  {"SKI WARD":{"closed":true}},
  {"WACHUSETT":{"trails":20,"lifts":5,"new snow":0,"depth":20}},
  {"ATTITASH":{"trails":36,"lifts":2,"new snow":0,"depth":0}},
  {"BRETTON WOODS":{"trails":39,"lifts":2,"new snow":0,"depth":16}},
  {"BLACK MOUNTAIN NH":{"trails":30,"lifts":3,"new snow":0,"depth":24}},
  {"CANNON MOUNTAIN":{"trails":0,"lifts":0,"new snow":0,"depth":0}},
  {"CRANMORE":{"trails":0,"lifts":0,"new snow":0,"depth":0}},
  {"CROTCHED":{"closed":true}},
  {"DARTMOUTH SKIWAY":{"closed":true}},
  {"GUNSTOCK":{"trails":41,"lifts":6,"new snow":0,"depth":16}},
  {"KING PINE":{"closed":true}},
  {"LOON":{"trails":38,"lifts":6,"new snow":0,"depth":0}},
  {"MCINTYRE":{"closed":true}},
  {"MOUNT SUNAPEE":{"trails":15,"lifts":2,"new snow":0,"depth":30}},
  {"PATS PEAK":{"closed":true}},
  {"RAGGED MOUNTAIN":{"trails":27,"lifts":5,"new snow":0,"depth":6}},
  {"TENNEY MOUNTAIN":{"trails":14,"lifts":2,"new snow":0,"depth":0}},
  {"WATERVILLE VALLEY":{"trails":58,"lifts":4,"new snow":0,"depth":12}},
  {"WHALEBACK":{"closed":true}},
  {"WILDCAT":{"trails":13,"lifts":2,"new snow":0,"depth":12}},
  {"YAWGOO VALLEY":{"closed":true}},
  {"BOLTON VALLEY":{"trails":37,"lifts":6,"new snow":0,"depth":25}},
  {"BROMLEY":{"trails":6,"lifts":1,"new snow":0,"depth":18}},
  {"BURKE":{"trails":31,"lifts":3,"new snow":0,"depth":24}},
  {"JAY PEAK":{"trails":49,"lifts":6,"new snow":0,"depth":16}},
  {"KILLINGTON":{"trails":83,"lifts":16,"new snow":0,"depth":25}},
  {"MAD RIVER GLEN":{"trails":0,"lifts":0,"new snow":0,"depth":0}},
  {"MAGIC MOUNTAIN":{"trails":6,"lifts":0,"new snow":0,"depth":0}},
  {"MIDDLEBURY SNOW BOWL":{"trails":8,"lifts":2,"new snow":0,"depth":0}},
  {"MOUNT SNOW":{"trails":13,"lifts":3,"new snow":0,"depth":24}},
  {"OKEMO":{"trails":66,"lifts":7,"new snow":0,"depth":36}},
  {"PICO":{"trails":14,"lifts":4,"new snow":0,"depth":0}},
  {"SASKADENA SIX":{"closed":true}},
  {"SMUGGLERS NOTCH":{"trails":20,"lifts":3,"new snow":0,"depth":12}},
  {"STOWE":{"trails":46,"lifts":8,"new snow":0,"depth":48}},
  {"STRATTON":{"trails":34,"lifts":3,"new snow":0,"depth":20}},
  {"SUGARBUSH":{"trails":34,"lifts":6,"new snow":0,"depth":12}}
]
