[
    {
        "MOHAWK MOUNTAIN": {
            "trails": 9,
            "lifts": 4
        }
    },
    {
        "MOUNT SOUTHINGTON": {
            "trails": 0,
            "lifts": 0,
            "depth": 0
        }
    },
    {
        "POWDER RIDGE": {
            "trails": 0,
            "lifts": 0
        }
    },
    {
        "SKI SUNDOWN": {
            "trails": 14,
            "lifts": 5,
            "depth": 6,
            "new snow": 0
        }
    },
    {
        "BIG MOOSE MOUNTAIN": {
            "trails": 19,
            "lifts": 2,
            "depth": 0.0,
            "new snow": 0.0
        }
    },
    {
        "BIGROCK": {
            "trails": 0,
            "lifts": 0,
            "depth": 0,
            "new snow": 0.0
        }
    },
    {
        "BLACK MOUNTAIN ME": {
            "lifts": 2,
            "trails": 10,
            "depth": " 12",
            "new snow": ""
        }
    },
    {
        "CAMDEN SNOW BOWL": {
            "lifts": 0,
            "trails": 0,
            "depth": 0
        }
    },
    {
        "LOST VALLEY": {
            "trails": "21",
            "lifts": "3"
        }
    },
    {
        "MOUNT ABRAM": {
            "trails": 14,
            "lifts": 3
        }
    },
    {
        "PLEASANT MOUNTAIN": {
            "lifts": 6,
            "trails": 33
        }
    },
    {
        "SADDLEBACK": {
            "lifts": 6,
            "trails": 37,
            "new snow": 0,
            "depth": 32
        }
    },
    {
        "SUGARLOAF": {
            "trails": 48,
            "lifts": 8
        }
    },
    {
        "SUNDAY RIVER": {
            "trails": 87,
            "lifts": 12
        }
    },
    {
        "BERKSHIRE EAST": {
            "trails": 22,
            "lifts": 4,
            "depth": "",
            "new snow": ""
        }
    },
    {
        "BLUE HILLS": {
            "trails": 0,
            "lifts": 0,
            "depth": 0.0,
            "new snow": 0.0
        }
    },
    {
        "BOUSQUET": {
            "trails": 12,
            "lifts": 3
        }
    },
    {
        "CATAMOUNT": {
            "trails": 14,
            "lifts": 3,
            "depth": 6.0,
            "new snow": 0.0
        }
    },
    {
        "JIMINY PEAK": {
            "trails": 32,
            "lifts": 4,
            "depth": 12,
            "new snow": 0
        }
    },
    {
        "NASHOBA VALLEY": {
            "trails": 0,
            "lifts": 0,
            "depth": 0,
            "new snow": 0
        }
    },
    {
        "SKI BRADFORD": {
            "trails": 0,
            "lifts": 0,
            "depth": 0,
            "new snow": 0
        }
    },
    {
        "BUTTERNUT": {
            "trails": 14,
            "lifts": 4,
            "depth": 10,
            "new snow": 0
        }
    },
    {
        "SKI WARD": {
            "trails": "0",
            "lifts": "0",
            "depth": "24"
        }
    },
    {
        "WACHUSETT": {
            "trails": 21,
            "lifts": 6,
            "depth": 35,
            "new snow": 0
        }
    },
    {
        "ATTITASH": {
            "trails": 53,
            "lifts": 3,
            "depth": 47,
            "new snow": 0
        }
    },
    {
        "BRETTON WOODS": {
            "trails": 37,
            "lifts": 5,
            "depth": 0,
            "new snow": 0
        }
    },
    {
        "BLACK MOUNTAIN NH": {
            "trails": "26",
            "lifts": "4",
            "new snow": ""
        }
    },
    {
        "CANNON MOUNTAIN": {
            "trails": 48,
            "lifts": 7,
            "depth": "",
            "new snow": ""
        }
    },
    {
        "CRANMORE": {
            "trails": "46",
            "lifts": "4",
            "depth": "23",
            "new snow": ""
        }
    },
    {
        "CROTCHED": {
            "trails": 16,
            "lifts": 3,
            "depth": 24,
            "new snow": 0
        }
    },
    {
        "DARTMOUTH SKIWAY": {
            "lifts": 3,
            "trails": 5,
            "new snow": 0
        }
    },
    {
        "GUNSTOCK": {
            "trails": 39,
            "lifts": 6,
            "depth": 20,
            "new snow": 0.0
        }
    },
    {
        "KING PINE": {
            "trails": 17,
            "lifts": 6,
            "depth": 20,
            "new snow": 0
        }
    },
    {
        "LOON": {
            "lifts": 11,
            "trails": 53,
            "new snow": 0
        }
    },
    {
        "MCINTYRE": {
            "trails": 11,
            "lifts": 4
        }
    },
    {
        "MOUNT SUNAPEE": {
            "trails": 48,
            "lifts": 7,
            "depth": 0,
            "new snow": 0
        }
    },
    {
        "PATS PEAK": {
            "trails": 28,
            "lifts": 9,
            "depth": 0,
            "new snow": 0
        }
    },
    {
        "RAGGED MOUNTAIN": {
            "trails": "30",
            "lifts": 5,
            "depth": "10",
            "new snow": "0"
        }
    },
    {
        "TENNEY MOUNTAIN": {
            "trails": 13,
            "lifts": 2
        }
    },
    {
        "WATERVILLE VALLEY": {
            "trails": 54,
            "lifts": 6,
            "depth": 12,
            "new snow": 0
        }
    },
    {
        "WHALEBACK": {
            "trails": "0",
            "lifts": "0"
        }
    },
    {
        "WILDCAT": {
            "trails": 8,
            "lifts": 2,
            "depth": 12,
            "new snow": 0
        }
    },
    {
        "YAWGOO VALLEY": {
            "trails": 0,
            "lifts": 0
        }
    },
    {
        "BOLTON VALLEY": {
            "trails": "35",
            "lifts": "5",
            "depth": "20",
            "new snow": "0"
        }
    },
    {
        "BROMLEY": {
            "trails": 33,
            "lifts": 4,
            "depth": 12,
            "new snow": 0.0
        }
    },
    {
        "BURKE": {
            "lifts": 3,
            "trails": 22,
            "new snow": 5
        }
    },
    {
        "JAY PEAK": {
            "trails": 75,
            "lifts": 8,
            "depth": 24,
            "new snow": 6
        }
    },
    {
        "KILLINGTON": {
            "lifts": 17,
            "trails": 105
        }
    },
    {
        "MAD RIVER GLEN": {
            "trails": 19,
            "lifts": 4,
            "new snow": 0
        }
    },
    {
        "MAGIC MOUNTAIN": {
            "trails": 9,
            "lifts": 1,
            "new snow": 0
        }
    },
    {
        "MIDDLEBURY SNOW BOWL": {
            "trails": 9,
            "lifts": 3
        }
    },
    {
        "MOUNT SNOW": {
            "trails": 44,
            "lifts": 9,
            "depth": 24,
            "new snow": 0
        }
    },
    {
        "OKEMO": {
            "trails": 98,
            "lifts": 17,
            "depth": 0,
            "new snow": 0
        }
    },
    {
        "PICO": {
            "trails": "23",
            "lifts": "5",
            "base depth": 30,
            "new snow": 0
        }
    },
    {
        "SASKADENA SIX": {
            "lifts": 2,
            "trails": 14
        }
    },
    {
        "SMUGGLERS NOTCH": {
            "trails": 31,
            "lifts": 7,
            "new snow": 0,
            "depth": 0
        }
    },
    {
        "STOWE": {
            "trails": 60,
            "lifts": 10,
            "depth": 48,
            "new snow": 1
        }
    },
    {
        "STRATTON": {
            "trails": 40,
            "lifts": 8,
            "depth": 20.0
        }
    },
    {
        "SUGARBUSH": {
            "trails": 68,
            "lifts": 12,
            "depth": 24.0,
            "new snow": 1.0
        }
    }
]
