[{"MOHAWK MOUNTAIN": {"trails": 16, "lifts": 5}}, {"MOUNT SOUTHINGTON": {"trails": 14, "lifts": 5, "depth": 24}}, {"POWDER RIDGE": {"trails": 14, "lifts": 5, "depth": 12}}, {"SKI SUNDOWN": {"trails": 16, "lifts": 5, "depth": 24, "new snow": 0}}, {"BIGROCK": {"trails": 10, "lifts": 3, "depth": 20, "new snow": 1.0}}, {"BLACK MOUNTAIN ME": {"lifts": 2, "trails": 30, "depth": " 15", "new snow": ""}}, {"CAMDEN SNOW BOWL": {"lifts": 1, "trails": 1, "new snow": "12-24"}}, {"LOST VALLEY": {"trails": "17", "lifts": "3"}}, {"MOUNT ABRAM": {"trails": 44, "lifts": 4}}, {"SADDLEBACK": {"lifts": 6, "trails": 66, "new snow": 0, "depth": 28}}, {"PLEASANT MOUNTAIN": {"trails": 36, "lifts": 5, "new snow": 0}}, {"SUGARLOAF": {"lifts": 8, "trails": 124, "depth": "", "new snow": ""}}, {"SUNDAY RIVER": {"trails": 115, "lifts": 11, "new snow": 0}}, {"BERKSHIRE EAST": {"trails": 28, "lifts": 4, "depth": "", "new snow": ""}}, {"BOUSQUET": {"trails": 14, "lifts": 4}}, {"CATAMOUNT": {"trails": 26, "lifts": 3, "depth": 12.0, "new snow": 0}}, {"JIMINY PEAK": {"trails": 35, "lifts": 5, "depth": 18, "new snow": 0}}, {"NASHOBA VALLEY": {"trails": 12, "lifts": 5, "depth": 26, "new snow": 0}}, {"BRADFORD": {"trails": 3}}, {"BUTTERNUT": {"trails": 20, "lifts": 5, "depth": 24, "new snow": 0}}, {"SKI WARD": {"trails": "9", "lifts": "4", "depth": "12"}}, {"WACHUSETT": {"trails": 25, "lifts": 5, "depth": 48, "new snow": 2}}, {"ATTITASH": {"trails": 40, "lifts": 7, "depth": 18, "new snow": 0}}, {"BRETTON WOODS": {"trails": 62, "lifts": 8, "depth": 18, "new snow": 0}}, {"BLACK MOUNTAIN NH": {"trails": "37", "lifts": "3", "new snow": ""}}, {"CANNON MOUNTAIN": {"trails": 55, "lifts": 5, "depth": 30, "new snow": 0}}, {"CRANMORE": {"trails": "40", "lifts": "4", "depth": "20", "new snow": ""}}, {"CROTCHED": {"trails": 25, "lifts": 3, "depth": 32, "new snow": 0}}, {"DARTMOUTH SKIWAY": {"lifts": 4, "trails": 26, "new snow": 0}}, {"KING PINE": {"trails": 12, "lifts": 4, "depth": 24, "new snow": 0}}, {"LOON": {"lifts": 8, "trails": 54, "new snow": 0}}, {"MOUNT SUNAPEE": {"trails": 43, "lifts": 8, "depth": 45, "new snow": 0}}, {"PATS PEAK": {"lifts": 0, "trails": 0, "depth": "", "new snow": ""}}, {"RAGGED MOUNTAIN": {"trails": "27", "lifts": 5, "depth": "14", "new snow": "0"}}, {"WATERVILLE VALLEY": {"trails": 57, "lifts": 7, "depth": 18, "new snow": 0}}, {"WHALEBACK": {"lifts": 0, "trails": 0, "depth": "", "new snow": ""}}, {"WILDCAT": {"lifts": 3, "trails": 45, "depth": "", "new snow": ""}}, {"YAWGOO VALLEY": {"trails": 9, "lifts": 1}}, {"BOLTON VALLEY": {"trails": "55", "lifts": "5", "depth": "24", "new snow": "0"}}, {"BROMLEY": {"trails": 44, "lifts": 3, "depth": 21, "new snow": 0}}, {"BURKE": {"trails": 53, "lifts": 4}}, {"JAY PEAK": {"trails": 75, "lifts": 7, "depth": 28, "new snow": 0}}, {"KILLINGTON": {"trails": 148, "lifts": 13, "depth": 16, "new snow": 0}}, {"MAD RIVER GLEN": {"trails": 54, "lifts": 3, "new snow": 0}}, {"MAGIC MOUNTAIN": {"trails": 50, "lifts": 3, "new snow": 0}}, {"MIDDLEBURY SNOW BOWL": {"lifts": 0, "trails": 0, "depth": "", "new snow": ""}}, {"MOUNT SNOW": {"lifts": 9, "trails": 60, "depth": "", "new snow": ""}}, {"OKEMO": {"trails": 105, "lifts": 13, "depth": 0, "new snow": 0}}, {"SMUGGLERS NOTCH": {"trails": 67, "lifts": 5, "new snow": 0}}, {"STOWE": {"trails": 111, "lifts": 11, "depth": 24, "new snow": 0}}, {"STRATTON": {"trails": 80, "lifts": 8, "depth": 18.0}}, {"SUGARBUSH": {"trails": 106, "lifts": 11, "depth": 24.0, "new snow": 0.0}}]