[
    {
        "MOHAWK MOUNTAIN": {
            "trails": 0,
            "lifts": 0
        }
    },
    {
        "MOUNT SOUTHINGTON": {
            "trails": 0,
            "lifts": 0,
            "depth": 0
        }
    },
    {
        "POWDER RIDGE": {
            "trails": 0,
            "lifts": 0
        }
    },
    {
        "SKI SUNDOWN": {
            "trails": 0,
            "lifts": 0,
            "depth": 24,
            "new snow": 0
        }
    },
    {
        "BIG MOOSE MOUNTAIN": {
            "trails": 19,
            "lifts": 2,
            "depth": 0.0,
            "new snow": 0.0
        }
    },
    {
        "BIGROCK": {
            "trails": 7,
            "lifts": 3,
            "depth": 12,
            "new snow": 0.0
        }
    },
    {
        "BLACK MOUNTAIN ME": {
            "lifts": 0,
            "trails": 0,
            "depth": " 12",
            "new snow": ""
        }
    },
    {
        "CAMDEN SNOW BOWL": {
            "lifts": 0,
            "trails": 0,
            "depth": 0
        }
    },
    {
        "LOST VALLEY": {
            "trails": "21",
            "lifts": "3"
        }
    },
    {
        "MOUNT ABRAM": {
            "trails": 15,
            "lifts": 3
        }
    },
    {
        "PLEASANT MOUNTAIN": {
            "lifts": 4,
            "trails": 27
        }
    },
    {
        "SADDLEBACK": {
            "lifts": 0,
            "trails": 31,
            "new snow": 0,
            "depth": 32
        }
    },
    {
        "SUGARLOAF": {
            "trails": 47,
            "lifts": 6
        }
    },
    {
        "SUNDAY RIVER": {
            "trails": 86,
            "lifts": 14
        }
    },
    {
        "BERKSHIRE EAST": {
            "trails": 29,
            "lifts": 0,
            "depth": "",
            "new snow": ""
        }
    },
    {
        "BLUE HILLS": {
            "trails": 0,
            "lifts": 0,
            "depth": 0.0,
            "new snow": 0.0
        }
    },
    {
        "BOUSQUET": {
            "trails": 15,
            "lifts": 0
        }
    },
    {
        "CATAMOUNT": {
            "trails": 0,
            "lifts": 0,
            "depth": 6.0,
            "new snow": 0.0
        }
    },
    {
        "JIMINY PEAK": {
            "trails": 33,
            "lifts": 4,
            "depth": 14,
            "new snow": 0
        }
    },
    {
        "NASHOBA VALLEY": {
            "trails": 0,
            "lifts": 0,
            "depth": 0,
            "new snow": 0
        }
    },
    {
        "SKI BRADFORD": {
            "trails": 0,
            "lifts": 0,
            "depth": 0,
            "new snow": 0
        }
    },
    {
        "BUTTERNUT": {
            "trails": 0,
            "lifts": 0,
            "depth": 0,
            "new snow": 0
        }
    },
    {
        "SKI WARD": {
            "trails": "0",
            "lifts": "0",
            "depth": "0"
        }
    },
    {
        "WACHUSETT": {
            "trails": 21,
            "lifts": 5,
            "depth": 40,
            "new snow": 0
        }
    },
    {
        "ATTITASH": {
            "trails": 59,
            "lifts": 6,
            "depth": 47,
            "new snow": 0
        }
    },
    {
        "BRETTON WOODS": {
            "trails": 39,
            "lifts": 4,
            "depth": 0,
            "new snow": 0
        }
    },
    {
        "BLACK MOUNTAIN NH": {
            "trails": "33",
            "lifts": "4",
            "new snow": ""
        }
    },
    {
        "CANNON MOUNTAIN": {
            "trails": 49,
            "lifts": 5,
            "depth": "",
            "new snow": ""
        }
    },
    {
        "CRANMORE": {
            "trails": "49",
            "lifts": "3",
            "depth": 0,
            "new snow": ""
        }
    },
    {
        "CROTCHED": {
            "trails": 17,
            "lifts": 3,
            "depth": 24,
            "new snow": 0
        }
    },
    {
        "DARTMOUTH SKIWAY": {
            "lifts": 0,
            "trails": 0,
            "new snow": 0
        }
    },
    {
        "GUNSTOCK": {
            "trails": 35,
            "lifts": 6,
            "depth": 30,
            "new snow": 0.0
        }
    },
    {
        "KING PINE": {
            "trails": 17,
            "lifts": 4,
            "depth": 30,
            "new snow": 0
        }
    },
    {
        "LOON": {
            "lifts": 9,
            "trails": 48,
            "new snow": 0
        }
    },
    {
        "MCINTYRE": {
            "trails": 0,
            "lifts": 0
        }
    },
    {
        "MOUNT SUNAPEE": {
            "trails": 48,
            "lifts": 7,
            "depth": 0,
            "new snow": 0
        }
    },
    {
        "PATS PEAK": {
            "trails": 28,
            "lifts": 4,
            "depth": 0,
            "new snow": 0
        }
    },
    {
        "RAGGED MOUNTAIN": {
            "trails": "31",
            "lifts": 5,
            "depth": "10",
            "new snow": "0"
        }
    },
    {
        "TENNEY MOUNTAIN": {
            "trails": 12,
            "lifts": 1
        }
    },
    {
        "WATERVILLE VALLEY": {
            "trails": 54,
            "lifts": 6,
            "depth": 12,
            "new snow": 0
        }
    },
    {
        "WHALEBACK": {
            "trails": "0",
            "lifts": "0"
        }
    },
    {
        "WILDCAT": {
            "trails": 9,
            "lifts": 2,
            "depth": 12,
            "new snow": 0
        }
    },
    {
        "YAWGOO VALLEY": {
            "trails": 0,
            "lifts": 0
        }
    },
    {
        "BOLTON VALLEY": {
            "trails": "34",
            "lifts": "5",
            "depth": "20",
            "new snow": "0"
        }
    },
    {
        "BROMLEY": {
            "trails": 36,
            "lifts": 3,
            "depth": 12,
            "new snow": 0.0
        }
    },
    {
        "BURKE": {
            "lifts": 3,
            "trails": 21,
            "new snow": 0
        }
    },
    {
        "JAY PEAK": {
            "trails": 71,
            "lifts": 8,
            "depth": 24,
            "new snow": 0
        }
    },
    {
        "KILLINGTON": {
            "lifts": 14,
            "trails": 119
        }
    },
    {
        "MAD RIVER GLEN": {
            "trails": 42,
            "lifts": 3,
            "new snow": 0
        }
    },
    {
        "MAGIC MOUNTAIN": {
            "trails": 17,
            "lifts": 2,
            "new snow": 0
        }
    },
    {
        "MIDDLEBURY SNOW BOWL": {
            "trails": 11,
            "lifts": 2
        }
    },
    {
        "MOUNT SNOW": {
            "trails": 54,
            "lifts": 7,
            "depth": 24,
            "new snow": 0
        }
    },
    {
        "OKEMO": {
            "trails": 106,
            "lifts": 10,
            "depth": 0,
            "new snow": 0
        }
    },
    {
        "PICO": {
            "trails": "27",
            "lifts": "4",
            "base depth": 31,
            "new snow": 0
        }
    },
    {
        "SASKADENA SIX": {
            "lifts": 2,
            "trails": 18
        }
    },
    {
        "SMUGGLERS NOTCH": {
            "trails": 20,
            "lifts": 4,
            "new snow": 0,
            "depth": 0
        }
    },
    {
        "STOWE": {
            "trails": 67,
            "lifts": 9,
            "depth": 48,
            "new snow": 0
        }
    },
    {
        "STRATTON": {
            "trails": 58,
            "lifts": 6,
            "depth": 24.0
        }
    },
    {
        "SUGARBUSH": {
            "trails": 81,
            "lifts": 10,
            "depth": 28.0,
            "new snow": 0.0
        }
    }
]
